nr_common/__init__.py
nr_common/alembic/7b1bed025ddd_create_nusl_branch.py
nr_common/alembic/b37580dba0f8_nusl_id_provider.py
nr_common/jsonschemas/__init__.py
nr_common/jsonschemas/nr_common/__init__.py
nr_common/jsonschemas/nr_common/nr-common-v1.0.0.json
nr_common/links.py
nr_common/mapping_includes/__init__.py
nr_common/mapping_includes/v7/__init__.py
nr_common/mapping_includes/v7/nr-common-v1.0.0.json
nr_common/mappings/__init__.py
nr_common/mappings/v7/__init__.py
nr_common/mappings/v7/nr_common/__init__.py
nr_common/marshmallow/__init__.py
nr_common/marshmallow/fields.py
nr_common/marshmallow/json.py
nr_common/marshmallow/subschemas.py
nr_common/minters.py
nr_common/models.py
nr_common/permissions.py
nr_common/providers.py
nr_common/search.py
techlib_nr_common-3.0.0a48.dist-info/entry_points.txt
techlib_nr_common-3.0.0a48.dist-info/WHEEL
techlib_nr_common-3.0.0a48.dist-info/METADATA
techlib_nr_common-3.0.0a48.dist-info/RECORD
